saf/AgentDefinition.py
saf/__init__.py
saf/py.typed
saf_python_sdk-0.1.0.dist-info/METADATA
saf_python_sdk-0.1.0.dist-info/WHEEL
saf_python_sdk-0.1.0.dist-info/RECORD
