Metadata-Version: 2.4
Name: saf-python-sdk
Version: 0.1.0
Summary: Structured Agent Framework for Python to build LLM/AI agents
Author-email: Quanzheng Long <qlong@indeed.com>
Requires-Python: >=3.12
